{
  "TF1.fr": "tf1-19",
  "France2.fr": "france-2-6",
  "France3.fr": "france-3-7",
  "France4.fr": "france-4-8",
  "France5.fr": "france-5-9",
  "M6.fr": "m6-12",
  "Arte.fr": "arte-337",
  "LaChaineParlementaire.fr": "la-chaine-parlementaire-11",
  "W9.fr": "w9-24",
  "TMC.fr": "tmc-21",
  "TFX.fr": "tfx-14",
  "Gulli.fr": "gulli-29",
  "BFMTV.fr": "bfmtv-25",
  "CNews.fr": "cnews-30",
  "LCI.fr": "lci-la-chaine-info-78",
  "FranceInfo.fr": "franceinfo-307",
  "CSTAR.fr": "cstar-28",
  "T18.fr": "t18-11532",
  "NOVO19.fr": "novo19-11533",
  "TF1SeriesFilms.fr": "tf1-series-films-201",
  "LEquipe21.fr": "lequipe-204",
  "6ter.fr": "6ter-202",
  "Numero23.fr": "rmc-story-203",
  "RMCDecouverte.fr": "rmc-decouverte-205",
  "RTL9.fr": "rtl-9-17",
  "CanalPlus.fr": "canalplus-2",
  "CanalPlusSport.fr": "canalplus-sport-37",
  "CanalPlusBoxOffice.fr": "canalplus-box-office-11522",
  "CanalPlusCinema.fr": "canalplus-cinema-35",
  "PlanetePlus.fr": "planeteplus-16",
  "ParisPremiere.fr": "paris-premiere-15",
  "CinePlusFrisson.fr": "cineplus-frisson-47"
}